escudeiro-0.4.0.dist-info/METADATA
escudeiro-0.4.0.dist-info/WHEEL
escudeiro-0.4.0.dist-info/licenses/LICENSE.md
escudeiro.libs/libgcc_s-39080030.so.1
escudeiro/__init__.py
escudeiro/__version__.py
escudeiro/autodiscovery/__init__.py
escudeiro/autodiscovery/base.py
escudeiro/autodiscovery/runtime.py
escudeiro/autodiscovery/static.py
escudeiro/config/__init__.py
escudeiro/config/adapter/__init__.py
escudeiro/config/adapter/attrs.py
escudeiro/config/adapter/cache.py
escudeiro/config/adapter/dataclass.py
escudeiro/config/adapter/factory.py
escudeiro/config/adapter/interface.py
escudeiro/config/adapter/pydantic.py
escudeiro/config/adapter/squire.py
escudeiro/config/concepts.py
escudeiro/config/core/__init__.py
escudeiro/config/core/config.py
escudeiro/config/core/context.py
escudeiro/config/core/envconfig.py
escudeiro/config/core/mapping.py
escudeiro/config/core/utils.py
escudeiro/config/interface.py
escudeiro/context/__init__.py
escudeiro/context/atomic_.py
escudeiro/context/bound.py
escudeiro/context/context.py
escudeiro/context/helper.py
escudeiro/context/interfaces.py
escudeiro/contrib/__init__.py
escudeiro/contrib/msgspec.py
escudeiro/contrib/pydantic.py
escudeiro/data/__init__.py
escudeiro/data/converters/__init__.py
escudeiro/data/converters/json.py
escudeiro/data/converters/utils.py
escudeiro/data/field_.py
escudeiro/data/helpers.py
escudeiro/data/main.py
escudeiro/data/methods.py
escudeiro/data/resolver.py
escudeiro/data/schema.py
escudeiro/data/slots.py
escudeiro/data/utils/factory.py
escudeiro/data/utils/functions.py
escudeiro/data/utils/typedef.py
escudeiro/ds/__init__.py
escudeiro/ds/circuit.py
escudeiro/ds/filetree/__init__.py
escudeiro/ds/filetree/filetree.py
escudeiro/ds/filetree/helpers.py
escudeiro/ds/filetree/virtual.py
escudeiro/ds/manager.py
escudeiro/ds/pools/__init__.py
escudeiro/ds/pools/asyncio.py
escudeiro/ds/pools/resource.py
escudeiro/ds/pools/thread.py
escudeiro/ds/registry.py
escudeiro/ds/scheduler.py
escudeiro/ds/sentinels.py
escudeiro/ds/worker.py
escudeiro/escudeiro_pyrs.cpython-313t-aarch64-linux-musl.so
escudeiro/escudeiro_pyrs.pyi
escudeiro-0.4.0.dist-info/RECORD
