Metadata-Version: 2.4
Name: escudeiro
Version: 0.4.0
Requires-Dist: orjson>=3.11.4
Requires-Dist: typing-extensions>=4.14.0
Requires-Dist: pydantic>=2.0.0,<3.0.0 ; extra == 'pydantic'
Requires-Dist: msgspec>=0.19.0,<1.0.0 ; extra == 'msgspec'
Provides-Extra: pydantic
Provides-Extra: msgspec
License-File: LICENSE.md
Summary: The squire to your python projects.
Author-email: Gustavo Cardoso <dev.guscardvs@proton.me>
License-Expression: Apache License 2.0
Requires-Python: >=3.12, <4.0.0
Project-URL: github, https://github.com/guscardvs/escudeiro
